{
  "name": "customers",
  "base": "PersistedModel",
  "idInjection": true,
  "options": {
    "validateUpsert": true
  },
  "properties": {
    "email": {
      "type": "string",
      "required": true
    },
    "password": {
      "type": "string",
      "required": true
    },
    "name": {
      "type": "string",
      "required": true
    },
    "avatar": {
      "type": "string"
    },
    "balance": {
      "type": "number",
      "default": 0
    },
    "createdAt": {
      "type": "date"
    },
    "phones": {
      "type": [
        "number"
      ]
    }
  },
  "validations": [],
  "relations": {},
  "acls": [],
  "methods": {}
}
